{
  "gitSyncId": "69b43dbe8090126bad399758_270e6170-7f22-4dc5-a542-3ad8d4ae0445",
  "id": "Dashboard_JS_Scoring.coverage",
  "pluginId": "js-plugin",
  "pluginType": "JS",
  "unpublishedAction": {
    "actionConfiguration": {
      "encodeParamsToggle": true,
      "jsArguments": [
        {
          "name": "openPipelineARR"
        },
        {
          "name": "bookingsARR"
        },
        {
          "name": "bookingsTarget"
        },
        {
          "name": "selfServiceARR"
        }
      ],
      "paginationType": "NONE",
      "timeoutInMillisecond": 10000
    },
    "collectionId": "Dashboard_JS_Scoring",
    "confirmBeforeExecute": false,
    "datasource": {
      "isAutoGenerated": false,
      "name": "UNUSED_DATASOURCE",
      "pluginId": "js-plugin"
    },
    "dynamicBindingPathList": [
      {
        "key": "body"
      }
    ],
    "fullyQualifiedName": "JS_Scoring.coverage",
    "name": "coverage",
    "pageId": "Dashboard",
    "runBehaviour": "MANUAL",
    "userSetOnLoad": false
  }
}